CHANGES.rst
MANIFEST.in
README.rst
setup.cfg
setup.py
Products/__init__.py
Products.RedirectionTool.egg-info/PKG-INFO
Products.RedirectionTool.egg-info/SOURCES.txt
Products.RedirectionTool.egg-info/dependency_links.txt
Products.RedirectionTool.egg-info/entry_points.txt
Products.RedirectionTool.egg-info/namespace_packages.txt
Products.RedirectionTool.egg-info/not-zip-safe
Products.RedirectionTool.egg-info/requires.txt
Products.RedirectionTool.egg-info/top_level.txt
Products/RedirectionTool/RedirectionTool.py
Products/RedirectionTool/__init__.py
Products/RedirectionTool/configure.zcml
Products/RedirectionTool/interfaces.py
Products/RedirectionTool/permissions.py
Products/RedirectionTool/rebuild_i18n.sh
Products/RedirectionTool/setuphandlers.py
Products/RedirectionTool/browser/__init__.py
Products/RedirectionTool/browser/manage-redirects.pt
Products/RedirectionTool/browser/redirects-controlpanel.pt
Products/RedirectionTool/browser/redirects.py
Products/RedirectionTool/locales/RedirectionTool.pot
Products/RedirectionTool/locales/manual.pot
Products/RedirectionTool/locales/cs/LC_MESSAGES/RedirectionTool.mo
Products/RedirectionTool/locales/cs/LC_MESSAGES/RedirectionTool.po
Products/RedirectionTool/locales/da/LC_MESSAGES/RedirectionTool.mo
Products/RedirectionTool/locales/da/LC_MESSAGES/RedirectionTool.po
Products/RedirectionTool/locales/de/LC_MESSAGES/RedirectionTool.mo
Products/RedirectionTool/locales/de/LC_MESSAGES/RedirectionTool.po
Products/RedirectionTool/locales/es/LC_MESSAGES/RedirectionTool.mo
Products/RedirectionTool/locales/es/LC_MESSAGES/RedirectionTool.po
Products/RedirectionTool/locales/eu/LC_MESSAGES/RedirectionTool.mo
Products/RedirectionTool/locales/eu/LC_MESSAGES/RedirectionTool.po
Products/RedirectionTool/locales/fr/LC_MESSAGES/RedirectionTool.mo
Products/RedirectionTool/locales/fr/LC_MESSAGES/RedirectionTool.po
Products/RedirectionTool/locales/nl/LC_MESSAGES/RedirectionTool.mo
Products/RedirectionTool/locales/nl/LC_MESSAGES/RedirectionTool.po
Products/RedirectionTool/locales/no/LC_MESSAGES/RedirectionTool.mo
Products/RedirectionTool/locales/no/LC_MESSAGES/RedirectionTool.po
Products/RedirectionTool/locales/pt_BR/LC_MESSAGES/RedirectionTool.mo
Products/RedirectionTool/locales/pt_BR/LC_MESSAGES/RedirectionTool.po
Products/RedirectionTool/profiles/default/actionicons.xml
Products/RedirectionTool/profiles/default/actions.xml
