Metadata-Version: 1.1
Name: Products.RedirectionTool
Version: 1.4.1
Summary: The Redirection Tool allows the management of the aliases stored in plone.app.redirector
Home-page: https://github.com/collective/Products.RedirectionTool
Author: Jarn AS
Author-email: info@jarn.com
License: GPL
Keywords: Redirection Alias Zope Plone
Platform: UNKNOWN
Classifier: Development Status :: 5 - Production/Stable
Classifier: Environment :: Web Environment
Classifier: Framework :: Plone
Classifier: Framework :: Plone :: 4.2
Classifier: Framework :: Plone :: 4.3
Classifier: Framework :: Plone :: 5.0
Classifier: Intended Audience :: System Administrators
Classifier: License :: OSI Approved :: GNU General Public License (GPL)
Classifier: Operating System :: OS Independent
Classifier: Programming Language :: Python
Classifier: Programming Language :: Python :: 2.7
Classifier: Topic :: Software Development :: Libraries :: Python Modules
